.hgtags
README
setup.py
tkwidgettree/__init__.py
tkwidgettree/fileparser.py
tkwidgettree/tkwidgettree.py
tkwidgettree.egg-info/PKG-INFO
tkwidgettree.egg-info/SOURCES.txt
tkwidgettree.egg-info/dependency_links.txt
tkwidgettree.egg-info/top_level.txt