Metadata-Version: 1.1
Name: tkwidgettree
Version: 1.0.0b2
Summary: Convenience class for building Tk widgets trees from a dict or a JSON file
Home-page: https://github.com/sthomen/tkwidgettree
Author: Staffan Thomen
Author-email: duck@shangtai.net
License: BSD
Keywords: Tk tkinter widget builder
Platform: UNKNOWN
Classifier: Development Status :: 4 - Beta
Classifier: Intended Audience :: Developers
Classifier: Programming Language :: Python :: 3
